falcon_pagination_processor/__init__.py
falcon_pagination_processor/middleware.py
falcon_pagination_processor-0.0.1.dist-info/LICENSE
falcon_pagination_processor-0.0.1.dist-info/METADATA
falcon_pagination_processor-0.0.1.dist-info/WHEEL
falcon_pagination_processor-0.0.1.dist-info/top_level.txt
falcon_pagination_processor-0.0.1.dist-info/RECORD
