Metadata-Version: 2.1
Name: falcon-pagination-processor
Version: 0.0.1
Summary: Pagination middleware for falcon resources.
Home-page: https://neetjn.github.io/falcon-pagination-processor/
Author: John Nolette
Author-email: john@neetgroup.net
License: MIT
Platform: UNKNOWN
Classifier: Development Status :: 4 - Beta
Classifier: Intended Audience :: Developers
Classifier: Programming Language :: Python :: 2.7
Classifier: Programming Language :: Python :: 3.6
